{
  "@context": "http://iiif.io/api/presentation/3/context.json",
  "id": "https://hipstas.github.io/annotating-adler/annotations/selection-from-script-interpretation-class-a-doll-s-house-by-henrik-ibsen-canvas-1-theory-and-technique.json",
  "type": "AnnotationPage",
  "label": "Theory and Technique",
  "items": [
    {
      "@context": "http://www.w3.org/ns/anno.jsonld",
      "id": "selection-from-script-interpretation-class-a-doll-s-house-by-henrik-ibsen-canvas-1-theory-and-technique-annotation-0.json",
      "type": "Annotation",
      "motivation": [
        "supplementing",
        "commenting"
      ],
      "body": {
        "type": "TextualBody",
        "value": "“Where did she come from? Why did she leave? Who is she?”",
        "format": "text/plain",
        "purpose": "commenting"
      },
      "target": {
        "source": {
          "id": "https://hipstas.github.io/annotating-adler/selection-from-script-interpretation-class-a-doll-s-house-by-henrik-ibsen/canvas-1/canvas",
          "type": "Canvas",
          "partOf": [
            {
              "id": "https://annotatingadler.github.io/adler-project/selection-from-script-interpretation-class-a-doll-s-house-by-henrik-ibsen/manifest.json",
              "type": "Manifest"
            }
          ]
        },
        "selector": {
          "type": "RangeSelector",
          "t": "600.0,1200.0"
        }
      }
    },
    {
      "@context": "http://www.w3.org/ns/anno.jsonld",
      "id": "selection-from-script-interpretation-class-a-doll-s-house-by-henrik-ibsen-canvas-1-theory-and-technique-annotation-1.json",
      "type": "Annotation",
      "motivation": [
        "supplementing",
        "commenting"
      ],
      "body": {
        "type": "TextualBody",
        "value": "Mention importance of understanding middle class for social situation of the play.",
        "format": "text/plain",
        "purpose": "commenting"
      },
      "target": {
        "source": {
          "id": "https://hipstas.github.io/annotating-adler/selection-from-script-interpretation-class-a-doll-s-house-by-henrik-ibsen/canvas-1/canvas",
          "type": "Canvas",
          "partOf": [
            {
              "id": "https://annotatingadler.github.io/adler-project/selection-from-script-interpretation-class-a-doll-s-house-by-henrik-ibsen/manifest.json",
              "type": "Manifest"
            }
          ]
        },
        "selector": {
          "type": "RangeSelector",
          "t": "1080.0,1620.0"
        }
      }
    },
    {
      "@context": "http://www.w3.org/ns/anno.jsonld",
      "id": "selection-from-script-interpretation-class-a-doll-s-house-by-henrik-ibsen-canvas-1-theory-and-technique-annotation-2.json",
      "type": "Annotation",
      "motivation": [
        "supplementing",
        "commenting"
      ],
      "body": {
        "type": "TextualBody",
        "value": "[Reading from script] “It’s really me” now, something happens to ME’, perspective shift.",
        "format": "text/plain",
        "purpose": "commenting"
      },
      "target": {
        "source": {
          "id": "https://hipstas.github.io/annotating-adler/selection-from-script-interpretation-class-a-doll-s-house-by-henrik-ibsen/canvas-1/canvas",
          "type": "Canvas",
          "partOf": [
            {
              "id": "https://annotatingadler.github.io/adler-project/selection-from-script-interpretation-class-a-doll-s-house-by-henrik-ibsen/manifest.json",
              "type": "Manifest"
            }
          ]
        },
        "selector": {
          "type": "RangeSelector",
          "t": "2820.0,3119.0"
        }
      }
    },
    {
      "@context": "http://www.w3.org/ns/anno.jsonld",
      "id": "selection-from-script-interpretation-class-a-doll-s-house-by-henrik-ibsen-canvas-1-theory-and-technique-annotation-3.json",
      "type": "Annotation",
      "motivation": [
        "supplementing",
        "commenting"
      ],
      "body": {
        "type": "TextualBody",
        "value": "Another mention of middle class as “ethical” and “honest”.",
        "format": "text/plain",
        "purpose": "commenting"
      },
      "target": {
        "source": {
          "id": "https://hipstas.github.io/annotating-adler/selection-from-script-interpretation-class-a-doll-s-house-by-henrik-ibsen/canvas-1/canvas",
          "type": "Canvas",
          "partOf": [
            {
              "id": "https://annotatingadler.github.io/adler-project/selection-from-script-interpretation-class-a-doll-s-house-by-henrik-ibsen/manifest.json",
              "type": "Manifest"
            }
          ]
        },
        "selector": {
          "type": "RangeSelector",
          "t": "4080.0,4800.0"
        }
      }
    },
    {
      "@context": "http://www.w3.org/ns/anno.jsonld",
      "id": "selection-from-script-interpretation-class-a-doll-s-house-by-henrik-ibsen-canvas-1-theory-and-technique-annotation-4.json",
      "type": "Annotation",
      "motivation": [
        "supplementing",
        "commenting"
      ],
      "body": {
        "type": "TextualBody",
        "value": "Employs first person perspective of character to ask questions, the method and becoming the character instead of affective memory.",
        "format": "text/plain",
        "purpose": "commenting"
      },
      "target": {
        "source": {
          "id": "https://hipstas.github.io/annotating-adler/selection-from-script-interpretation-class-a-doll-s-house-by-henrik-ibsen/canvas-1/canvas",
          "type": "Canvas",
          "partOf": [
            {
              "id": "https://annotatingadler.github.io/adler-project/selection-from-script-interpretation-class-a-doll-s-house-by-henrik-ibsen/manifest.json",
              "type": "Manifest"
            }
          ]
        },
        "selector": {
          "type": "RangeSelector",
          "t": "4620.0,5520.0"
        }
      }
    },
    {
      "@context": "http://www.w3.org/ns/anno.jsonld",
      "id": "selection-from-script-interpretation-class-a-doll-s-house-by-henrik-ibsen-canvas-1-theory-and-technique-annotation-5.json",
      "type": "Annotation",
      "motivation": [
        "supplementing",
        "commenting"
      ],
      "body": {
        "type": "TextualBody",
        "value": "“And I have a lot of words but I have more than that”, and begins analysis of Nora’s character, delves into familial background and lack of it and can infer the class implications of being an orphan.",
        "format": "text/plain",
        "purpose": "commenting"
      },
      "target": {
        "source": {
          "id": "https://hipstas.github.io/annotating-adler/selection-from-script-interpretation-class-a-doll-s-house-by-henrik-ibsen/canvas-1/canvas",
          "type": "Canvas",
          "partOf": [
            {
              "id": "https://annotatingadler.github.io/adler-project/selection-from-script-interpretation-class-a-doll-s-house-by-henrik-ibsen/manifest.json",
              "type": "Manifest"
            }
          ]
        },
        "selector": {
          "type": "RangeSelector",
          "t": "7860.0,10080.0"
        }
      }
    },
    {
      "@context": "http://www.w3.org/ns/anno.jsonld",
      "id": "selection-from-script-interpretation-class-a-doll-s-house-by-henrik-ibsen-canvas-1-theory-and-technique-annotation-6.json",
      "type": "Annotation",
      "motivation": [
        "supplementing",
        "commenting"
      ],
      "body": {
        "type": "TextualBody",
        "value": "“There is no you”, you’re only the character, pretty clear idea of the method coming out.",
        "format": "text/plain",
        "purpose": "commenting"
      },
      "target": {
        "source": {
          "id": "https://hipstas.github.io/annotating-adler/selection-from-script-interpretation-class-a-doll-s-house-by-henrik-ibsen/canvas-1/canvas",
          "type": "Canvas",
          "partOf": [
            {
              "id": "https://annotatingadler.github.io/adler-project/selection-from-script-interpretation-class-a-doll-s-house-by-henrik-ibsen/manifest.json",
              "type": "Manifest"
            }
          ]
        },
        "selector": {
          "type": "RangeSelector",
          "t": "8880.0,9420.0"
        }
      }
    },
    {
      "@context": "http://www.w3.org/ns/anno.jsonld",
      "id": "selection-from-script-interpretation-class-a-doll-s-house-by-henrik-ibsen-canvas-1-theory-and-technique-annotation-7.json",
      "type": "Annotation",
      "motivation": [
        "supplementing",
        "commenting"
      ],
      "body": {
        "type": "TextualBody",
        "value": "Tries to make a point about the importance of “giving up you” but mocks herself for a moment, good humour about these things.",
        "format": "text/plain",
        "purpose": "commenting"
      },
      "target": {
        "source": {
          "id": "https://hipstas.github.io/annotating-adler/selection-from-script-interpretation-class-a-doll-s-house-by-henrik-ibsen/canvas-1/canvas",
          "type": "Canvas",
          "partOf": [
            {
              "id": "https://annotatingadler.github.io/adler-project/selection-from-script-interpretation-class-a-doll-s-house-by-henrik-ibsen/manifest.json",
              "type": "Manifest"
            }
          ]
        },
        "selector": {
          "type": "RangeSelector",
          "t": "9480.0,10020.0"
        }
      }
    },
    {
      "@context": "http://www.w3.org/ns/anno.jsonld",
      "id": "selection-from-script-interpretation-class-a-doll-s-house-by-henrik-ibsen-canvas-1-theory-and-technique-annotation-8.json",
      "type": "Annotation",
      "motivation": [
        "supplementing",
        "commenting"
      ],
      "body": {
        "type": "TextualBody",
        "value": "“I don’t know anything but I have now the beginning that… who is she? What do I have to find out about her?”",
        "format": "text/plain",
        "purpose": "commenting"
      },
      "target": {
        "source": {
          "id": "https://hipstas.github.io/annotating-adler/selection-from-script-interpretation-class-a-doll-s-house-by-henrik-ibsen/canvas-1/canvas",
          "type": "Canvas",
          "partOf": [
            {
              "id": "https://annotatingadler.github.io/adler-project/selection-from-script-interpretation-class-a-doll-s-house-by-henrik-ibsen/manifest.json",
              "type": "Manifest"
            }
          ]
        },
        "selector": {
          "type": "RangeSelector",
          "t": "10200.0,10740.0"
        }
      }
    },
    {
      "@context": "http://www.w3.org/ns/anno.jsonld",
      "id": "selection-from-script-interpretation-class-a-doll-s-house-by-henrik-ibsen-canvas-1-theory-and-technique-annotation-9.json",
      "type": "Annotation",
      "motivation": [
        "supplementing",
        "commenting"
      ],
      "body": {
        "type": "TextualBody",
        "value": "“There is no me.”",
        "format": "text/plain",
        "purpose": "commenting"
      },
      "target": {
        "source": {
          "id": "https://hipstas.github.io/annotating-adler/selection-from-script-interpretation-class-a-doll-s-house-by-henrik-ibsen/canvas-1/canvas",
          "type": "Canvas",
          "partOf": [
            {
              "id": "https://annotatingadler.github.io/adler-project/selection-from-script-interpretation-class-a-doll-s-house-by-henrik-ibsen/manifest.json",
              "type": "Manifest"
            }
          ]
        },
        "selector": {
          "type": "RangeSelector",
          "t": "10560.0,10740.0"
        }
      }
    },
    {
      "@context": "http://www.w3.org/ns/anno.jsonld",
      "id": "selection-from-script-interpretation-class-a-doll-s-house-by-henrik-ibsen-canvas-1-theory-and-technique-annotation-10.json",
      "type": "Annotation",
      "motivation": [
        "supplementing",
        "commenting"
      ],
      "body": {
        "type": "TextualBody",
        "value": "“I’m beginning to break through that I have to get to the background”, can see the method at work here and Adler’s emphasis on research.",
        "format": "text/plain",
        "purpose": "commenting"
      },
      "target": {
        "source": {
          "id": "https://hipstas.github.io/annotating-adler/selection-from-script-interpretation-class-a-doll-s-house-by-henrik-ibsen/canvas-1/canvas",
          "type": "Canvas",
          "partOf": [
            {
              "id": "https://annotatingadler.github.io/adler-project/selection-from-script-interpretation-class-a-doll-s-house-by-henrik-ibsen/manifest.json",
              "type": "Manifest"
            }
          ]
        },
        "selector": {
          "type": "RangeSelector",
          "t": "10620.0,11099.0"
        }
      }
    },
    {
      "@context": "http://www.w3.org/ns/anno.jsonld",
      "id": "selection-from-script-interpretation-class-a-doll-s-house-by-henrik-ibsen-canvas-1-theory-and-technique-annotation-11.json",
      "type": "Annotation",
      "motivation": [
        "supplementing",
        "commenting"
      ],
      "body": {
        "type": "TextualBody",
        "value": "Look at how environment and differences impact a character, leads back to things like class and relationships, also reaches out to class to check in that they are understanding.",
        "format": "text/plain",
        "purpose": "commenting"
      },
      "target": {
        "source": {
          "id": "https://hipstas.github.io/annotating-adler/selection-from-script-interpretation-class-a-doll-s-house-by-henrik-ibsen/canvas-1/canvas",
          "type": "Canvas",
          "partOf": [
            {
              "id": "https://annotatingadler.github.io/adler-project/selection-from-script-interpretation-class-a-doll-s-house-by-henrik-ibsen/manifest.json",
              "type": "Manifest"
            }
          ]
        },
        "selector": {
          "type": "RangeSelector",
          "t": "11160.0,12479.0"
        }
      }
    },
    {
      "@context": "http://www.w3.org/ns/anno.jsonld",
      "id": "selection-from-script-interpretation-class-a-doll-s-house-by-henrik-ibsen-canvas-1-theory-and-technique-annotation-12.json",
      "type": "Annotation",
      "motivation": [
        "supplementing",
        "commenting"
      ],
      "body": {
        "type": "TextualBody",
        "value": "Historical context of war and possible impact it had on men in society.",
        "format": "text/plain",
        "purpose": "commenting"
      },
      "target": {
        "source": {
          "id": "https://hipstas.github.io/annotating-adler/selection-from-script-interpretation-class-a-doll-s-house-by-henrik-ibsen/canvas-1/canvas",
          "type": "Canvas",
          "partOf": [
            {
              "id": "https://annotatingadler.github.io/adler-project/selection-from-script-interpretation-class-a-doll-s-house-by-henrik-ibsen/manifest.json",
              "type": "Manifest"
            }
          ]
        },
        "selector": {
          "type": "RangeSelector",
          "t": "13380.0,14580.0"
        }
      }
    },
    {
      "@context": "http://www.w3.org/ns/anno.jsonld",
      "id": "selection-from-script-interpretation-class-a-doll-s-house-by-henrik-ibsen-canvas-1-theory-and-technique-annotation-13.json",
      "type": "Annotation",
      "motivation": [
        "supplementing",
        "commenting"
      ],
      "body": {
        "type": "TextualBody",
        "value": "Historical context on Norway and Ibsen, serious and emotional again, explains impacts war had on Ibsen.",
        "format": "text/plain",
        "purpose": "commenting"
      },
      "target": {
        "source": {
          "id": "https://hipstas.github.io/annotating-adler/selection-from-script-interpretation-class-a-doll-s-house-by-henrik-ibsen/canvas-1/canvas",
          "type": "Canvas",
          "partOf": [
            {
              "id": "https://annotatingadler.github.io/adler-project/selection-from-script-interpretation-class-a-doll-s-house-by-henrik-ibsen/manifest.json",
              "type": "Manifest"
            }
          ]
        },
        "selector": {
          "type": "RangeSelector",
          "t": "15060.0,15780.0"
        }
      }
    },
    {
      "@context": "http://www.w3.org/ns/anno.jsonld",
      "id": "selection-from-script-interpretation-class-a-doll-s-house-by-henrik-ibsen-canvas-1-theory-and-technique-annotation-14.json",
      "type": "Annotation",
      "motivation": [
        "supplementing",
        "commenting"
      ],
      "body": {
        "type": "TextualBody",
        "value": "“It’s in the text”, process of questioning + revisiting text multiple times.",
        "format": "text/plain",
        "purpose": "commenting"
      },
      "target": {
        "source": {
          "id": "https://hipstas.github.io/annotating-adler/selection-from-script-interpretation-class-a-doll-s-house-by-henrik-ibsen/canvas-1/canvas",
          "type": "Canvas",
          "partOf": [
            {
              "id": "https://annotatingadler.github.io/adler-project/selection-from-script-interpretation-class-a-doll-s-house-by-henrik-ibsen/manifest.json",
              "type": "Manifest"
            }
          ]
        },
        "selector": {
          "type": "RangeSelector",
          "t": "15360.0,15720.0"
        }
      }
    },
    {
      "@context": "http://www.w3.org/ns/anno.jsonld",
      "id": "selection-from-script-interpretation-class-a-doll-s-house-by-henrik-ibsen-canvas-1-theory-and-technique-annotation-15.json",
      "type": "Annotation",
      "motivation": [
        "supplementing",
        "commenting"
      ],
      "body": {
        "type": "TextualBody",
        "value": "Historical research/context applied to characterization.",
        "format": "text/plain",
        "purpose": "commenting"
      },
      "target": {
        "source": {
          "id": "https://hipstas.github.io/annotating-adler/selection-from-script-interpretation-class-a-doll-s-house-by-henrik-ibsen/canvas-1/canvas",
          "type": "Canvas",
          "partOf": [
            {
              "id": "https://annotatingadler.github.io/adler-project/selection-from-script-interpretation-class-a-doll-s-house-by-henrik-ibsen/manifest.json",
              "type": "Manifest"
            }
          ]
        },
        "selector": {
          "type": "RangeSelector",
          "t": "25200.0,26820.0"
        }
      }
    },
    {
      "@context": "http://www.w3.org/ns/anno.jsonld",
      "id": "selection-from-script-interpretation-class-a-doll-s-house-by-henrik-ibsen-canvas-1-theory-and-technique-annotation-16.json",
      "type": "Annotation",
      "motivation": [
        "supplementing",
        "commenting"
      ],
      "body": {
        "type": "TextualBody",
        "value": "The “truth” used here, applied to script.",
        "format": "text/plain",
        "purpose": "commenting"
      },
      "target": {
        "source": {
          "id": "https://hipstas.github.io/annotating-adler/selection-from-script-interpretation-class-a-doll-s-house-by-henrik-ibsen/canvas-1/canvas",
          "type": "Canvas",
          "partOf": [
            {
              "id": "https://annotatingadler.github.io/adler-project/selection-from-script-interpretation-class-a-doll-s-house-by-henrik-ibsen/manifest.json",
              "type": "Manifest"
            }
          ]
        },
        "selector": {
          "type": "RangeSelector",
          "t": "29100.0,29760.0"
        }
      }
    },
    {
      "@context": "http://www.w3.org/ns/anno.jsonld",
      "id": "selection-from-script-interpretation-class-a-doll-s-house-by-henrik-ibsen-canvas-1-theory-and-technique-annotation-17.json",
      "type": "Annotation",
      "motivation": [
        "supplementing",
        "commenting"
      ],
      "body": {
        "type": "TextualBody",
        "value": "Looking out and addressing the classroom very directly and very still, revelatory statement about Nora.",
        "format": "text/plain",
        "purpose": "commenting"
      },
      "target": {
        "source": {
          "id": "https://hipstas.github.io/annotating-adler/selection-from-script-interpretation-class-a-doll-s-house-by-henrik-ibsen/canvas-1/canvas",
          "type": "Canvas",
          "partOf": [
            {
              "id": "https://annotatingadler.github.io/adler-project/selection-from-script-interpretation-class-a-doll-s-house-by-henrik-ibsen/manifest.json",
              "type": "Manifest"
            }
          ]
        },
        "selector": {
          "type": "RangeSelector",
          "t": "30720.0,31200.0"
        }
      }
    },
    {
      "@context": "http://www.w3.org/ns/anno.jsonld",
      "id": "selection-from-script-interpretation-class-a-doll-s-house-by-henrik-ibsen-canvas-1-theory-and-technique-annotation-18.json",
      "type": "Annotation",
      "motivation": [
        "supplementing",
        "commenting"
      ],
      "body": {
        "type": "TextualBody",
        "value": "Teacher voice again, very calm after drama, reveals that she calls it a “recognition scene”, seems to have worked through/figured out the scene as she’s teaching it.",
        "format": "text/plain",
        "purpose": "commenting"
      },
      "target": {
        "source": {
          "id": "https://hipstas.github.io/annotating-adler/selection-from-script-interpretation-class-a-doll-s-house-by-henrik-ibsen/canvas-1/canvas",
          "type": "Canvas",
          "partOf": [
            {
              "id": "https://annotatingadler.github.io/adler-project/selection-from-script-interpretation-class-a-doll-s-house-by-henrik-ibsen/manifest.json",
              "type": "Manifest"
            }
          ]
        },
        "selector": {
          "type": "RangeSelector",
          "t": "33000.0,33180.0"
        }
      }
    }
  ]
}