{
  "@context": "http://iiif.io/api/presentation/3/context.json",
  "id": "https://hipstas.github.io/annotating-adler/annotations/selection-from-script-interpretation-class-candida-by-george-bernard-shaw-ads0504--canvas-1-theory-and-technique.json",
  "type": "AnnotationPage",
  "label": "Theory and Technique",
  "items": [
    {
      "@context": "http://www.w3.org/ns/anno.jsonld",
      "id": "selection-from-script-interpretation-class-candida-by-george-bernard-shaw-ads0504--canvas-1-theory-and-technique-annotation-0.json",
      "type": "Annotation",
      "motivation": [
        "supplementing",
        "commenting"
      ],
      "body": [
        {
          "type": "TextualBody",
          "value": "Motif of \"size\" and possible point about religion ",
          "format": "text/plain",
          "purpose": "commenting"
        },
        {
          "type": "TextualBody",
          "value": "Size, Religion",
          "format": "text/plain",
          "purpose": "tagging"
        }
      ],
      "target": {
        "source": {
          "id": "https://hipstas.github.io/annotating-adler/selection-from-script-interpretation-class-candida-by-george-bernard-shaw-ads0504-/canvas-1/canvas",
          "type": "Canvas",
          "partOf": [
            {
              "id": "https://annotatingadler.github.io/adler-project/candida/manifest.json",
              "type": "Manifest"
            }
          ]
        },
        "selector": {
          "type": "RangeSelector",
          "t": "13.0,21.0"
        }
      }
    },
    {
      "@context": "http://www.w3.org/ns/anno.jsonld",
      "id": "selection-from-script-interpretation-class-candida-by-george-bernard-shaw-ads0504--canvas-1-theory-and-technique-annotation-1.json",
      "type": "Annotation",
      "motivation": [
        "supplementing",
        "commenting"
      ],
      "body": [
        {
          "type": "TextualBody",
          "value": "Script analysis and character analysis, character background",
          "format": "text/plain",
          "purpose": "commenting"
        },
        {
          "type": "TextualBody",
          "value": "Script Analysis, Characterization",
          "format": "text/plain",
          "purpose": "tagging"
        }
      ],
      "target": {
        "source": {
          "id": "https://hipstas.github.io/annotating-adler/selection-from-script-interpretation-class-candida-by-george-bernard-shaw-ads0504-/canvas-1/canvas",
          "type": "Canvas",
          "partOf": [
            {
              "id": "https://annotatingadler.github.io/adler-project/candida/manifest.json",
              "type": "Manifest"
            }
          ]
        },
        "selector": {
          "type": "RangeSelector",
          "t": "34.0,50.0"
        }
      }
    },
    {
      "@context": "http://www.w3.org/ns/anno.jsonld",
      "id": "selection-from-script-interpretation-class-candida-by-george-bernard-shaw-ads0504--canvas-1-theory-and-technique-annotation-2.json",
      "type": "Annotation",
      "motivation": [
        "supplementing",
        "commenting"
      ],
      "body": [
        {
          "type": "TextualBody",
          "value": "Takes moment to read over script then make points/draw conclusions about character",
          "format": "text/plain",
          "purpose": "commenting"
        },
        {
          "type": "TextualBody",
          "value": "Script Analysis, Characterization",
          "format": "text/plain",
          "purpose": "tagging"
        }
      ],
      "target": {
        "source": {
          "id": "https://hipstas.github.io/annotating-adler/selection-from-script-interpretation-class-candida-by-george-bernard-shaw-ads0504-/canvas-1/canvas",
          "type": "Canvas",
          "partOf": [
            {
              "id": "https://annotatingadler.github.io/adler-project/candida/manifest.json",
              "type": "Manifest"
            }
          ]
        },
        "selector": {
          "type": "RangeSelector",
          "t": "63.0,71.0"
        }
      }
    },
    {
      "@context": "http://www.w3.org/ns/anno.jsonld",
      "id": "selection-from-script-interpretation-class-candida-by-george-bernard-shaw-ads0504--canvas-1-theory-and-technique-annotation-3.json",
      "type": "Annotation",
      "motivation": [
        "supplementing",
        "commenting"
      ],
      "body": [
        {
          "type": "TextualBody",
          "value": "Talks about physicality and its relation to masculinity and specific masculinities (poet, artist, etc.)",
          "format": "text/plain",
          "purpose": "commenting"
        },
        {
          "type": "TextualBody",
          "value": "Masculinity",
          "format": "text/plain",
          "purpose": "tagging"
        }
      ],
      "target": {
        "source": {
          "id": "https://hipstas.github.io/annotating-adler/selection-from-script-interpretation-class-candida-by-george-bernard-shaw-ads0504-/canvas-1/canvas",
          "type": "Canvas",
          "partOf": [
            {
              "id": "https://annotatingadler.github.io/adler-project/candida/manifest.json",
              "type": "Manifest"
            }
          ]
        },
        "selector": {
          "type": "RangeSelector",
          "t": "79.0,87.0"
        }
      }
    },
    {
      "@context": "http://www.w3.org/ns/anno.jsonld",
      "id": "selection-from-script-interpretation-class-candida-by-george-bernard-shaw-ads0504--canvas-1-theory-and-technique-annotation-4.json",
      "type": "Annotation",
      "motivation": [
        "supplementing",
        "commenting"
      ],
      "body": [
        {
          "type": "TextualBody",
          "value": "More character analysis with focus on scripted behavior",
          "format": "text/plain",
          "purpose": "commenting"
        },
        {
          "type": "TextualBody",
          "value": "Physicality, Script Analysis",
          "format": "text/plain",
          "purpose": "tagging"
        }
      ],
      "target": {
        "source": {
          "id": "https://hipstas.github.io/annotating-adler/selection-from-script-interpretation-class-candida-by-george-bernard-shaw-ads0504-/canvas-1/canvas",
          "type": "Canvas",
          "partOf": [
            {
              "id": "https://annotatingadler.github.io/adler-project/candida/manifest.json",
              "type": "Manifest"
            }
          ]
        },
        "selector": {
          "type": "RangeSelector",
          "t": "93.0,105.0"
        }
      }
    },
    {
      "@context": "http://www.w3.org/ns/anno.jsonld",
      "id": "selection-from-script-interpretation-class-candida-by-george-bernard-shaw-ads0504--canvas-1-theory-and-technique-annotation-5.json",
      "type": "Annotation",
      "motivation": [
        "supplementing",
        "commenting"
      ],
      "body": [
        {
          "type": "TextualBody",
          "value": "More focus on physical aspects of character",
          "format": "text/plain",
          "purpose": "commenting"
        },
        {
          "type": "TextualBody",
          "value": "Physicality",
          "format": "text/plain",
          "purpose": "tagging"
        }
      ],
      "target": {
        "source": {
          "id": "https://hipstas.github.io/annotating-adler/selection-from-script-interpretation-class-candida-by-george-bernard-shaw-ads0504-/canvas-1/canvas",
          "type": "Canvas",
          "partOf": [
            {
              "id": "https://annotatingadler.github.io/adler-project/candida/manifest.json",
              "type": "Manifest"
            }
          ]
        },
        "selector": {
          "type": "RangeSelector",
          "t": "109.0,118.0"
        }
      }
    },
    {
      "@context": "http://www.w3.org/ns/anno.jsonld",
      "id": "selection-from-script-interpretation-class-candida-by-george-bernard-shaw-ads0504--canvas-1-theory-and-technique-annotation-6.json",
      "type": "Annotation",
      "motivation": [
        "supplementing",
        "commenting"
      ],
      "body": [
        {
          "type": "TextualBody",
          "value": "Advice to \"write down the physicality of each character\" while watching plays if physicality not in the script",
          "format": "text/plain",
          "purpose": "commenting"
        },
        {
          "type": "TextualBody",
          "value": "Physicality",
          "format": "text/plain",
          "purpose": "tagging"
        }
      ],
      "target": {
        "source": {
          "id": "https://hipstas.github.io/annotating-adler/selection-from-script-interpretation-class-candida-by-george-bernard-shaw-ads0504-/canvas-1/canvas",
          "type": "Canvas",
          "partOf": [
            {
              "id": "https://annotatingadler.github.io/adler-project/candida/manifest.json",
              "type": "Manifest"
            }
          ]
        },
        "selector": {
          "type": "RangeSelector",
          "t": "118.0,127.0"
        }
      }
    },
    {
      "@context": "http://www.w3.org/ns/anno.jsonld",
      "id": "selection-from-script-interpretation-class-candida-by-george-bernard-shaw-ads0504--canvas-1-theory-and-technique-annotation-7.json",
      "type": "Annotation",
      "motivation": [
        "supplementing",
        "commenting"
      ],
      "body": [
        {
          "type": "TextualBody",
          "value": "Once again emphasis on size/masculinity",
          "format": "text/plain",
          "purpose": "commenting"
        },
        {
          "type": "TextualBody",
          "value": "Size, Masculinity",
          "format": "text/plain",
          "purpose": "tagging"
        }
      ],
      "target": {
        "source": {
          "id": "https://hipstas.github.io/annotating-adler/selection-from-script-interpretation-class-candida-by-george-bernard-shaw-ads0504-/canvas-1/canvas",
          "type": "Canvas",
          "partOf": [
            {
              "id": "https://annotatingadler.github.io/adler-project/candida/manifest.json",
              "type": "Manifest"
            }
          ]
        },
        "selector": {
          "type": "RangeSelector",
          "t": "140.0,150.0"
        }
      }
    },
    {
      "@context": "http://www.w3.org/ns/anno.jsonld",
      "id": "selection-from-script-interpretation-class-candida-by-george-bernard-shaw-ads0504--canvas-1-theory-and-technique-annotation-8.json",
      "type": "Annotation",
      "motivation": [
        "supplementing",
        "commenting"
      ],
      "body": [
        {
          "type": "TextualBody",
          "value": "Class aspect in relation to size/masculinity",
          "format": "text/plain",
          "purpose": "commenting"
        },
        {
          "type": "TextualBody",
          "value": "Class",
          "format": "text/plain",
          "purpose": "tagging"
        }
      ],
      "target": {
        "source": {
          "id": "https://hipstas.github.io/annotating-adler/selection-from-script-interpretation-class-candida-by-george-bernard-shaw-ads0504-/canvas-1/canvas",
          "type": "Canvas",
          "partOf": [
            {
              "id": "https://annotatingadler.github.io/adler-project/candida/manifest.json",
              "type": "Manifest"
            }
          ]
        },
        "selector": {
          "type": "RangeSelector",
          "t": "154.0,161.0"
        }
      }
    }
  ]
}