{
  "@context": "http://iiif.io/api/presentation/3/context.json",
  "id": "https://hipstas.github.io/annotating-adler/annotations/selection-from-script-interpretation-class-a-doll-s-house-by-henrik-ibsen-ads0186--canvas-1-rhetorical-device.json",
  "type": "AnnotationPage",
  "label": "Rhetorical Device",
  "items": [
    {
      "@context": "http://www.w3.org/ns/anno.jsonld",
      "id": "selection-from-script-interpretation-class-a-doll-s-house-by-henrik-ibsen-ads0186--canvas-1-rhetorical-device-annotation-0.json",
      "type": "Annotation",
      "motivation": [
        "supplementing",
        "commenting"
      ],
      "body": [
        {
          "type": "TextualBody",
          "value": "Mentions extensive knowledge about Norway, obvious connection to Scandinavian theater/Ibsen, makes extended joke about Norway and how she should just teach the class about Norway, turns away from the class as she jokes",
          "format": "text/plain",
          "purpose": "commenting"
        },
        {
          "type": "TextualBody",
          "value": "Acting Voice",
          "format": "text/plain",
          "purpose": "tagging"
        }
      ],
      "target": {
        "source": {
          "id": "https://hipstas.github.io/annotating-adler/selection-from-script-interpretation-class-a-doll-s-house-by-henrik-ibsen-ads0186-/canvas-1/canvas",
          "type": "Canvas",
          "partOf": [
            {
              "id": "https://annotatingadler.github.io/adler-project/selection-from-script-interpretation-class-a-doll-s-house-by-henrik-ibsen-ads0186-/manifest.json",
              "type": "Manifest"
            }
          ]
        },
        "selector": {
          "type": "RangeSelector",
          "t": "11220.0,12000.0"
        }
      }
    },
    {
      "@context": "http://www.w3.org/ns/anno.jsonld",
      "id": "selection-from-script-interpretation-class-a-doll-s-house-by-henrik-ibsen-ads0186--canvas-1-rhetorical-device-annotation-1.json",
      "type": "Annotation",
      "motivation": [
        "supplementing",
        "commenting"
      ],
      "body": [
        {
          "type": "TextualBody",
          "value": "Mock acting again, this time taking on a Norwegian character to make a funny point to the class",
          "format": "text/plain",
          "purpose": "commenting"
        },
        {
          "type": "TextualBody",
          "value": "Dramatic Pause",
          "format": "text/plain",
          "purpose": "tagging"
        }
      ],
      "target": {
        "source": {
          "id": "https://hipstas.github.io/annotating-adler/selection-from-script-interpretation-class-a-doll-s-house-by-henrik-ibsen-ads0186-/canvas-1/canvas",
          "type": "Canvas",
          "partOf": [
            {
              "id": "https://annotatingadler.github.io/adler-project/selection-from-script-interpretation-class-a-doll-s-house-by-henrik-ibsen-ads0186-/manifest.json",
              "type": "Manifest"
            }
          ]
        },
        "selector": {
          "type": "RangeSelector",
          "t": "12060.0,12540.0"
        }
      }
    },
    {
      "@context": "http://www.w3.org/ns/anno.jsonld",
      "id": "selection-from-script-interpretation-class-a-doll-s-house-by-henrik-ibsen-ads0186--canvas-1-rhetorical-device-annotation-2.json",
      "type": "Annotation",
      "motivation": [
        "supplementing",
        "commenting"
      ],
      "body": [
        {
          "type": "TextualBody",
          "value": "Long pause, starting to get serious again after joking around, teaching voice back on",
          "format": "text/plain",
          "purpose": "commenting"
        },
        {
          "type": "TextualBody",
          "value": "Acting Voice",
          "format": "text/plain",
          "purpose": "tagging"
        }
      ],
      "target": {
        "source": {
          "id": "https://hipstas.github.io/annotating-adler/selection-from-script-interpretation-class-a-doll-s-house-by-henrik-ibsen-ads0186-/canvas-1/canvas",
          "type": "Canvas",
          "partOf": [
            {
              "id": "https://annotatingadler.github.io/adler-project/selection-from-script-interpretation-class-a-doll-s-house-by-henrik-ibsen-ads0186-/manifest.json",
              "type": "Manifest"
            }
          ]
        },
        "selector": {
          "type": "RangeSelector",
          "t": "14700.0,14880.0"
        }
      }
    },
    {
      "@context": "http://www.w3.org/ns/anno.jsonld",
      "id": "selection-from-script-interpretation-class-a-doll-s-house-by-henrik-ibsen-ads0186--canvas-1-rhetorical-device-annotation-3.json",
      "type": "Annotation",
      "motivation": [
        "supplementing",
        "commenting"
      ],
      "body": [
        {
          "type": "TextualBody",
          "value": "Breaks out of seriousness again as she realizes she has once again adopted Norwegianness (as the method would have it for her character), but nonetheless continues to explain background",
          "format": "text/plain",
          "purpose": "commenting"
        },
        {
          "type": "TextualBody",
          "value": "Teaching Voice, Script Analysis",
          "format": "text/plain",
          "purpose": "tagging"
        }
      ],
      "target": {
        "source": {
          "id": "https://hipstas.github.io/annotating-adler/selection-from-script-interpretation-class-a-doll-s-house-by-henrik-ibsen-ads0186-/canvas-1/canvas",
          "type": "Canvas",
          "partOf": [
            {
              "id": "https://annotatingadler.github.io/adler-project/selection-from-script-interpretation-class-a-doll-s-house-by-henrik-ibsen-ads0186-/manifest.json",
              "type": "Manifest"
            }
          ]
        },
        "selector": {
          "type": "RangeSelector",
          "t": "15839.0,16380.0"
        }
      }
    }
  ]
}